__init__.py
ailiteall/__init__.py
ailiteall/_ai_operations.py
ailiteall/_const.py
ailiteall/_main.py
ailiteall/_types.py
ailiteall/_unified_ai_api_server.py
ailiteall/ai_operations.py
ailiteall/_serve_models/__init__.py
ailiteall/_serve_models/_ollama_api.py
ailiteall/_serve_models/_openai_style.py
ailiteall/_support/__init__.py
ailiteall/_support/_autogen_support.py
ailiteall/_support/langchain_support.py
ailiteall/_support/llama_index_support.py
ailiteall-0.0.7.dist-info/LICENSE
ailiteall-0.0.7.dist-info/METADATA
ailiteall-0.0.7.dist-info/WHEEL
ailiteall-0.0.7.dist-info/top_level.txt
ailiteall-0.0.7.dist-info/RECORD
